{"absolute_value": 1, "absolute_value_add_sub": 2, "absolute_value_add_sub_properties": 3, "absolute_value_equations": 4, "absolute_value_of_complex_numbers": 5, "absolute_values_meaning": 6, "add_subtract_negative_fractions": 7, "adding_and_subtracting_centimeter_and_millimeter": 8, "adding_and_subtracting_complex_numbers": 9, "adding_and_subtracting_decimals_word_problems": 10, "adding_and_subtracting_fractions": 11, "adding_and_subtracting_negative_numbers": 12, "adding_and_subtracting_polynomials": 13, "adding_and_subtracting_radicals": 14, "adding_and_subtracting_within_20": 15, "adding_decimals": 16, "adding_decimals_0.5": 17, "adding_decimals_2": 18, "adding_fractions": 19, "adding_fractions_with_common_denominators": 20, "adding_negative_numbers": 21, "adding_subtracting_carry_2": 22, "adding_subtracting_carry_3": 23, "adding_subtracting_mixed_numbers_0.5": 24, "adding_subtracting_mixed_numbers_1": 25, "adding_subtracting_no_carry_3": 26, "adding_vectors": 27, "addition_1": 28, "addition_2": 29, "addition_3": 30, "addition_4": 31, "addition_of_vary_denominator_fraction": 32, "addition_two_numbers": 33, "addition_within_20": 34, "advanced_fraction": 35, "age_problems": 36, "age_problems_new": 37, "age_word_problems": 38, "alternate_exterior_angles": 39, "alternate_exterior_angles_2": 40, "alternate_interior_angles": 41, "alternate_interior_angles_2": 42, "altitude_and_hypotenuse": 43, "angle_addition_postulate": 44, "angle_bisector_theorem": 45, "angle_of_osculation": 46, "angle_rotation": 47, "angle_types": 48, "angles_1": 49, "angles_2": 50, "angles_of_a_polygon": 51, "application_add_large_nums": 52, "application_division_large_nums": 53, "application_of_linear_equations_1": 54, "application_of_linear_equations_2": 55, "application_of_scientific_notation": 56, "application_of_scientific_notation_2": 57, "applications_of_index": 58, "approximate_number": 59, "arc_length_and_circular_sector_area": 60, "area_1": 61, "area_of_a_circle": 62, "area_of_a_circle2": 63, "area_of_fans": 64, "area_of_parallelograms": 65, "area_of_squares_and_rectangles": 66, "area_of_triangles_1": 67, "area_of_triangular_shapes": 68, "area_relationship_larger_narrow_graph": 69, "area_relationship_larger_narrow_num": 70, "area_unit_cm_square": 71, "areas_of_circles_and_sectors": 72, "areas_of_kites": 73, "areas_of_rhombi": 74, "areas_of_trapezoids": 75, "areas_of_trapezoids_rhombi_and_kites": 76, "arithmetic_means": 77, "arithmetic_reasoning": 78, "arithmetic_sequences_3": 79, "arithmetic_series": 80, "arithmetic_series_1": 81, "arithmetic_word_problems": 82, "arithmetic_word_problems_1": 83, "arithmetic_word_problems_2": 84, "average_word_problems": 85, "axis_of_symmetry": 86, "baseline_compareline": 87, "baseline_compareline_application": 88, "basic_compared_with_the_reference_quantity": 89, "basic_concept_of_circumcenter": 90, "basic_concept_of_congruent_triangles": 91, "basic_concept_of_similar_shapes": 92, "basic_concepts_of_probability_1": 93, "basic_concepts_of_probability_2": 94, "basic_graph_and_composite_graph_area": 95, "calculating_averages_advanced": 96, "calculation_of_proportions": 97, "calculations_using_similar_shapes": 98, "chain_rule_1": 99, "chickens_and_rabbits_questions": 100, "circles_and_arcs": 101, "circumferential_angle": 102, "combinations_of_polynomials": 103, "combining_like_terms_1": 104, "combining_like_terms_2": 105, "combining_like_terms_with_two_variables": 106, "common_factor": 107, "common_factor_advance": 108, "common_form_for_life": 109, "comparing_absolute_values": 110, "comparing_fractions_1": 111, "comparing_fractions_2": 112, "comparing_improper_fractions_and_mixed_numbers": 113, "comparing_with_multiplication": 114, "comparison_between_numbers_within_ten": 115, "comparison_between_numbers_within_ten_0.5": 116, "complementary_and_supplementary_angles": 117, "complementary_angles": 118, "completing_the_square_1": 119, "completing_the_square_1_new": 120, "completing_the_square_2": 121, "complex_fraction": 122, "composite_numbers": 123, "compound_inequalities": 124, "computing_law_with_power": 125, "concepts_related_to_diamond": 126, "concepts_related_to_kite": 127, "concepts_related_to_parallelogram": 128, "conditional_statements_2": 129, "conditional_statements_and_truth_value": 130, "cone_surface_arc": 131, "congruency_postulates": 132, "congruent_angles": 133, "congruent_segments": 134, "congruent_triangles_1": 135, "congruent_triangles_2": 136, "constant_function_and_a_fuction": 137, "converse_inverse_and_contrapositive": 138, "converting_between_point_slope_and_slope_intercept": 139, "converting_between_slope_intercept_and_standard_form": 140, "converting_decimals_to_fractions_1": 141, "converting_decimals_to_fractions_2": 142, "converting_decimals_to_percents": 143, "converting_fractions_to_decimals": 144, "converting_mixed_numbers_and_improper_fractions": 145, "converting_percents_to_decimals": 146, "converting_repeating_decimals_to_fractions_1": 147, "converting_repeating_decimals_to_fractions_2": 148, "coordination_bctest_cap": 149, "corresponding_angles": 150, "corresponding_angles_2": 151, "count_number_to_100": 152, "count_number_to_20": 153, "count_number_to_20_2": 154, "count_number_to_50": 155, "count_numbers": 156, "count_one_by_one_1": 157, "counting_1": 158, "counting_2": 159, "creating_bar_charts_1": 160, "creating_box_and_whisker_plots": 161, "cross_multiplication_advanced": 162, "cube_roots": 163, "date_and_weekday": 164, "decimal_multiplier_calculation": 165, "decimal_two_steps": 166, "decimals_distributive_law_of_multiplication": 167, "decimals_on_the_number_line_1": 168, "decimals_on_the_number_line_2": 169, "define_one_function": 170, "definition_opposite_number": 171, "degrees_to_radians": 172, "denominator_comparison": 173, "dependent_probability": 174, "derivative_intuition": 175, "derivatives_1": 176, "direct_and_inverse_variation": 177, "discount_tax_and_tip_word_problems": 178, "distance_between_point_and_line": 179, "distance_formula": 180, "distributive_property": 181, "distributive_property_with_variables": 182, "dividing_complex_numbers": 183, "dividing_decimals": 184, "dividing_decimals_0.5": 185, "dividing_decimals_1": 186, "dividing_decimals_2": 187, "dividing_decimals_int_to_int_0.5": 188, "dividing_decimals_int_to_int_0.7": 189, "dividing_fractions": 190, "dividing_fractions_0.5": 191, "dividing_fractions_word_problems": 192, "dividing_polynomials": 193, "dividing_polynomials_1": 194, "dividing_polynomials_2": 195, "dividing_polynomials_3": 196, "dividing_polynomials_4": 197, "dividing_polynomials_5": 198, "dividing_polynomials_6": 199, "divisibility": 200, "divisibility_0.5": 201, "divisibility_intuition": 202, "divisibility_tests": 203, "division_0.5": 204, "division_0.9": 205, "division_1": 206, "division_1.4": 207, "division_1.5": 208, "division_2": 209, "division_2.9": 210, "division_3": 211, "division_4": 212, "division_word_problems_1": 213, "division_word_problems_2": 214, "domain_and_range_0.5": 215, "domain_of_a_function": 216, "draw_a_pie_chart": 217, "empirical_rule": 218, "equation_of_a_circle_1": 219, "equation_of_a_circle_2": 220, "equation_of_a_hyperbola": 221, "equation_of_a_line": 222, "equation_of_an_ellipse": 223, "equivalent_fractions": 224, "equivalent_fractions_2": 225, "equivalent_fractions_conversion": 226, "estimation_three-digit_add_sub": 227, "estimation_with_decimals": 228, "eval_expressions_w_two_var": 229, "evaluating_expressions_1": 230, "evaluating_expressions_2": 231, "even_and_odd_functions": 232, "exploring_angle_pairs_1": 233, "exploring_mean_and_median": 234, "exploring_standard_deviation_1": 235, "exponent_rules": 236, "exponents_1": 237, "exponents_2": 238, "exponents_3": 239, "exponents_4": 240, "expressing_ratios_as_fractions": 241, "expressions_with_unknown_variables": 242, "expressions_with_unknown_variables_2": 243, "factor_word_problems": 244, "factoring_difference_of_squares_1": 245, "factoring_difference_of_squares_2": 246, "factoring_difference_of_squares_3": 247, "factoring_polynomials_1": 248, "factoring_polynomials_2": 249, "factoring_polynomials_by_grouping_1": 250, "factoring_polynomials_with_two_variables": 251, "factorization_by_add_sub_square": 252, "factorization_quadratic_polynomial": 253, "finding_axis_of_symmetry": 254, "four_operations_and_decimal_fraction": 255, "fraction_integer": 256, "fraction_of_one_step_to_unknow_formula": 257, "fraction_word_problems_1": 258, "fractional_division_life_problem": 259, "fractions_cut_and_copy_1": 260, "fractions_cut_and_copy_2": 261, "fractions_on_the_number_line_1": 262, "fractions_on_the_number_line_2": 263, "fractions_on_the_number_line_3": 264, "fractions_word_problem": 265, "functions_1": 266, "functions_2": 267, "functions_3": 268, "gcd_and_lcm_word_problems": 269, "gcd_of_life": 270, "geometric_construction": 271, "geometry_1": 272, "geometry_about_circle_concept": 273, "geometry_categorial_proposition": 274, "geometry_identification_concept": 275, "geometry_proofs_1": 276, "geometry_proofs_2": 277, "geometry_proofs_intro": 278, "get_gcd_and_lcm": 279, "graphing_inequalities": 280, "graphing_inequalities_2": 281, "graphing_linear_equations": 282, "graphing_parabolas_0.5": 283, "graphing_parabolas_1": 284, "graphing_parabolas_2": 285, "graphing_points": 286, "graphing_points_2": 287, "graphing_points_fraction_1": 288, "graphing_points_fraction_2": 289, "graphing_scaling": 290, "graphing_systems_of_equations": 291, "graphing_systems_of_inequalities": 292, "graphing_systems_of_inequalities_2": 293, "graphs_of_linear_equations": 294, "graphs_of_sine_and_cosine": 295, "greatest_common_divisor": 296, "halves_and_fourths": 297, "herons_formula": 298, "hundred_million_adding_and_subtracting": 299, "identifying_points_1": 300, "identifying_points_2": 301, "imaginary_unit_powers": 302, "independent_probability": 303, "inequalities_and_expressions": 304, "inequalities_on_a_number_line": 305, "inequality_properties": 306, "inequality_symbol_word_problems": 307, "inscribed_angles_1": 308, "inscribed_angles_2": 309, "inscribed_angles_3": 310, "integer_arithmetic": 311, "integers_multiply_decimals": 312, "integers_multiply_decimals2": 313, "interpreting_linear_equations": 314, "inverse_proportional_calculation": 315, "inverse_trig_functions": 316, "inverses_of_functions": 317, "judging_axis_of_symmetry": 318, "kg_g_arithmatic": 319, "kg_g_time_div": 320, "kg_g_unit_transform": 321, "kg_g_unit_transform2": 322, "km_m_unit_transform": 323, "l_ml_arithmatic": 324, "l_ml_time_div": 325, "l_ml_transform": 326, "l_ml_word_problem": 327, "large_angle_long_edge": 328, "lcm_word_problems": 329, "least_common_multiple": 330, "least_common_multiple_and_greatest_common_divisor_word_problems": 331, "lhopitals_rule": 332, "life_1": 333, "limits_1": 334, "limits_2": 335, "line_graph_intuition": 336, "line_relationships": 337, "linear_equations_1": 338, "linear_equations_2": 339, "linear_equations_3": 340, "linear_equations_4": 341, "linear_equations_word_problems_2": 342, "linear_inequalities": 343, "lines_plane_vertical_parallel": 344, "logarithms_1": 345, "logarithms_2": 346, "logical_arguments_deductive_reasoning": 347, "make_a_line_by_ruler_and_compasses": 348, "marking_inequalities_range_on_a_number_line": 349, "markup_and_commission_word_problems": 350, "matrix_add_sub_2": 351, "matrix_add_sub_3": 352, "matrix_add_zero_negative": 353, "matrix_app_fruit_oil": 354, "matrix_basic_distance": 355, "matrix_basic_percentage": 356, "matrix_basic_product": 357, "matrix_gaussian_elimination": 358, "matrix_mul_scalar": 359, "matrix_mul_two": 360, "matrix_mul_two_2": 361, "matrix_mul_zero_one": 362, "matrix_row_echelon": 363, "matrix_row_operation": 364, "matrix_submatrix": 365, "matrix_transpose": 366, "matrix_triangular_and_symmetric": 367, "mean_median_and_mode": 368, "meaning_congruent_planar_graph": 369, "measuring_and_comparing_angles": 370, "measuring_angles": 371, "measuring_segments": 372, "meters_and_centimeters": 373, "metric_area_unit_comparison": 374, "metric_area_unit_conversion": 375, "metric_weight_unit_conversion": 376, "metric_weight_unit_selection": 377, "metric_weight_unit_word_problem": 378, "midpoint_coordinates": 379, "midpoint_formula": 380, "midpoint_of_a_segment": 381, "millimeter_and_centimeter": 382, "morning_afternoon_night": 383, "moving_points": 384, "multiple_brackets": 385, "multiple_proportions_reasoning": 386, "multiple_unit_transate": 387, "multiplication_0.5": 388, "multiplication_1": 389, "multiplication_1.5": 390, "multiplication_2": 391, "multiplication_3": 392, "multiplication_4": 393, "multiplication_and_division_order": 394, "multiplication_and_division_word_problems": 395, "multiplication_association_word_problems": 396, "multiplication_formula_1": 397, "multiplication_formula_add": 398, "multiplication_formula_minus": 399, "multiplication_formula_sub": 400, "multiplication_word_problems": 401, "multiplicative_problems": 402, "multiply_by_tens": 403, "multiplying_and_dividing": 404, "multiplying_and_dividing_negative_numbers": 405, "multiplying_and_dividing_scientific_notation": 406, "multiplying_complex_numbers": 407, "multiplying_decimal_integer": 408, "multiplying_decimals": 409, "multiplying_expressions_0.5": 410, "multiplying_expressions_1": 411, "multiplying_fractions": 412, "multiplying_fractions_0.5": 413, "multiplying_fractions_and_whole_numbers_word_problems": 414, "multiplying_fractions_word_problems": 415, "multiplying_mixed_numbers_1": 416, "multiplying_polynomials": 417, "multiplying_radicals": 418, "narrative_and_opposite_narrative": 419, "nature_of_isosceles_triangle": 420, "negative_number_word_problems": 421, "negative_numbers_multiply_divide": 422, "new_definitions_1": 423, "new_definitions_2": 424, "notation_calculation_type": 425, "number_line": 426, "number_line_0.5": 427, "number_line_0.7": 428, "number_line_2": 429, "number_line_3": 430, "number_line_4": 431, "number_properties_terminology_1": 432, "number_sequence_within_ten": 433, "number_within_fifty": 434, "one_more_one_less": 435, "one_step_equation_problems": 436, "one_step_equations": 437, "one_step_equations_0.5": 438, "one_step_inequalities": 439, "operations_with_negative_numbers": 440, "order_of_operations": 441, "ordering_fractions": 442, "ordering_improper_fractions_and_mixed_numbers": 443, "ordering_negative_numbers": 444, "ordering_numbers": 445, "parabola_intuition_1": 446, "parabola_intuition_2": 447, "parabola_intuition_3": 448, "parallel_and_perpendicular": 449, "parallel_lines_1": 450, "parallel_lines_2": 451, "parallel_lines_proportion": 452, "parallelogram_concept_and_application": 453, "parts_of_circles": 454, "percentage_concept": 455, "percentage_word_problems_1": 456, "percentage_word_problems_2": 457, "perimeter_1": 458, "perimeter_deduction": 459, "perimeter_of_combined_shapes": 460, "perimeter_of_sector": 461, "perimeter_of_squares_and_rectangles": 462, "permutations_1": 463, "place_value": 464, "place_value_big_number": 465, "place_value_concept": 466, "planar_graph_resizing": 467, "planting_problems": 468, "plotting_the_line_of_best_fit": 469, "plugging_in_values": 470, "point_slope_form": 471, "points_lines_and_planes": 472, "polygon_geometry_characteristic": 473, "polygon_similarity": 474, "polynomial_concept_and_proper_noun": 475, "position_relation_between_circle_point": 476, "power_rule": 477, "prime_factorization": 478, "prime_numbers": 479, "probability_1": 480, "product_rule": 481, "properties_of_incenters": 482, "properties_of_numbers_1": 483, "properties_of_numbers_2": 484, "proportional_calculation": 485, "proportional_life_problems": 486, "proportional_or_inverse_proportional": 487, "proportions_1": 488, "proportions_2": 489, "proportions_inner_outer_product": 490, "pyramidal_prism": 491, "pythagorean_theorem_1": 492, "quadratic_equation": 493, "quadratic_function_concept": 494, "quadratic_function_graphing": 495, "quadratic_function_maximum_and_minimum": 496, "quadratic_function_word_problem": 497, "quadratic_polynomial_word_problem": 498, "quadratics_word_problems": 499, "quadrilateral_angles": 500, "quadrilateral_types": 501, "quotient_rule": 502, "radians_and_degrees": 503, "radians_to_degrees": 504, "radical_equations": 505, "radical_multiplication_and_division": 506, "radius_and_diameter": 507, "radius_angle": 508, "radius_diameter_and_circumference": 509, "radius_diameter_and_circumference_1": 510, "radius_diameter_and_circumference_314_1": 511, "range_of_a_function": 512, "range_of_triangle_sides_2": 513, "range_quarter_case_chart": 514, "rate_problems_0.5": 515, "rate_problems_1": 516, "rate_problems_2": 517, "rate_unit_transform": 518, "rates_and_ratios": 519, "ratio": 520, "ratio_and_the_ratio_of": 521, "ratio_discount": 522, "ratio_money": 523, "ratio_word_problems": 524, "re_graphics": 525, "reading_bar_charts_1": 526, "reading_bar_charts_2": 527, "reading_bar_charts_3": 528, "reading_fractions_in_chinese": 529, "reading_line_charts_1": 530, "reading_pictographs_1": 531, "reading_pictographs_2": 532, "reading_stem_and_leaf_plots": 533, "reading_tables_1": 534, "reading_tables_2": 535, "realizing_inequalities": 536, "recognize_decimal_percentile_position": 537, "recognize_graph_zoom_effect": 538, "recognize_num_less_than_10000": 539, "recognizing_conic_sections": 540, "recognizing_factoring": 541, "recognizing_fractions": 542, "recognizing_fractions_0.5": 543, "recognizing_rays_lines_and_line_segments": 544, "recognizing_shapes": 545, "recording_life_problem_by_expressions": 546, "regrouping_decimals": 547, "regular_number_of_columns": 548, "relationships_linear_equations": 549, "represent_by_symbol_addend": 550, "represent_by_symbol_dividend": 551, "represent_by_symbol_multiplier": 552, "represent_by_symbol_subtrahend": 553, "representing_numbers": 554, "rounding_numbers": 555, "rounding_whole_numbers": 556, "same_side_exterior_angles": 557, "same_side_exterior_angles_2": 558, "same_side_interior_angles": 559, "same_side_interior_angles_2": 560, "scale": 561, "scaling_vectors": 562, "scientific_notation": 563, "scientific_notation_decimals": 564, "scientific_notation_intuition": 565, "sectors_as_fraction_of_circles_1": 566, "sectors_as_fraction_of_circles_2": 567, "segment_addition": 568, "separation_and_union": 569, "sequences_word_problems": 570, "shaded_areas": 571, "shifting_and_reflecting_functions": 572, "sides_and_angles_of_simple_shapes": 573, "significant_figures_1": 574, "similar_triangles_1": 575, "similar_triangles_2": 576, "similar_triangles_review": 577, "simple_hologram_concept": 578, "simple_hologram_surface_area": 579, "simplificate_ractional_formula": 580, "simplify_expressions_w_two_var_1": 581, "simplify_expressions_w_two_var_2": 582, "simplify_expressions_w_two_var_3": 583, "simplify_the_root_type": 584, "simplifying_expressions_with_exponents": 585, "simplifying_fractions": 586, "simplifying_radicals": 587, "skip_counting_by_10s": 588, "slope_intercept_form": 589, "slope_of_a_line": 590, "solid_geometry": 591, "solutions_to_systems_of_equations": 592, "solving_for_a_variable": 593, "solving_for_the_x-intercept": 594, "solving_for_the_y-intercept": 595, "solving_linear_equations": 596, "solving_linear_inequalities": 597, "solving_quadratics_by_factoring": 598, "solving_quadratics_by_factoring_2": 599, "solving_quadratics_by_taking_the_square_root": 600, "solving_similar_triangles_1": 601, "solving_similar_triangles_2": 602, "special_derivatives": 603, "special_right_triangles": 604, "special_triangle_and_quadrilateral_concept": 605, "speed_applying": 606, "speed_equal_to_distance_divide_time": 607, "square_cm_square_m_unit_transform": 608, "square_root_calculation_3": 609, "square_roots": 610, "square_roots_2": 611, "standard_deviation": 612, "statistical_table_and_chart": 613, "subtract_of_positive_negative_fraction": 614, "subtracting_decimals": 615, "subtracting_decimals_0.5": 616, "subtracting_fractions": 617, "subtracting_fractions_with_common_denominators": 618, "subtraction_1": 619, "subtraction_2": 620, "subtraction_3": 621, "subtraction_4": 622, "subtraction_and_addition": 623, "subtraction_of_vary_denominator_fraction": 624, "subtraction_within_20": 625, "supplementary_angles": 626, "surface_area_of_cylinders": 627, "surface_area_of_rectangular_boxes": 628, "symmetry_concept_and_application": 629, "systems_of_equ_elimination_1": 630, "systems_of_equ_substitution_1": 631, "systems_of_equ_substitution_2": 632, "systems_of_equations": 633, "systems_of_equations_with_elimination": 634, "systems_of_equations_with_elimination_0.5": 635, "systems_of_equations_with_elimination_2": 636, "systems_of_equations_with_elimination_3": 637, "systems_of_equations_with_substitution": 638, "systems_of_equations_word_problems": 639, "telling_time": 640, "telling_time_0.5": 641, "telling_time_2": 642, "telling_time_comparing": 643, "the_complex_plane": 644, "the_four_arithmetic_exponentially": 645, "the_fundamental_theorem_of_arithmetic": 646, "time_terminology": 647, "time_units_transformation_1": 648, "time_units_transformation_2": 649, "time_units_transformation_3": 650, "time_word_problem_1": 651, "time_word_problem_2": 652, "time_word_problem_3": 653, "time_word_problem_4": 654, "time_word_problem_5": 655, "trapezoid_concept_and_application": 656, "triangle_angles_1": 657, "triangle_angles_sum": 658, "triangle_central_core_concept": 659, "triangle_inequality_theorem": 660, "triangle_length_of_side": 661, "triangle_types": 662, "triangles_congruent_nature_aas": 663, "triangles_congruent_nature_asa": 664, "triangles_congruent_nature_rhs": 665, "triangles_congruent_nature_sas": 666, "triangles_congruent_nature_sss": 667, "triangles_similar_nature": 668, "trig_identities_1": 669, "trigonometry_0.5": 670, "trigonometry_1": 671, "trigonometry_1.5": 672, "trigonometry_2": 673, "understand_circle": 674, "understand_coins": 675, "understand_equivalent_axiom": 676, "understand_large_numbers_and_conversion": 677, "understand_length_unit": 678, "understand_range_of_graphie": 679, "understanding_comparing_angle": 680, "understanding_decimals_place_value": 681, "understanding_km": 682, "understanding_moving_the_decimal": 683, "understanding_square_rectangular": 684, "ungroup_median": 685, "unit_circle": 686, "unit_conversion_rate": 687, "units": 688, "variables_word_problems_1": 689, "variables_word_problems_2": 690, "variance": 691, "vector_add_sub_two": 692, "vertex_of_a_parabola": 693, "vertical_and_parallel": 694, "vertical_angles": 695, "vertical_angles_2": 696, "vertical_concepts": 697, "volume_and_cc": 698, "volume_box": 699, "volume_box_cover": 700, "volume_box_nocover": 701, "volume_container": 702, "volume_container_hight": 703, "volume_of_cylinders": 704, "volume_of_rectangular_boxes": 705, "volume_of_rectangular_boxes_2": 706, "volume_of_rectangular_boxes_3": 707, "volume_of_triangular_prisms": 708, "volume_space": 709, "volume_unit_conversion": 710, "word_problem_formula_translate": 711, "writing_and_interpreting_decimals": 712, "writing_expressions_1": 713, "writing_expressions_2": 714, "writing_expressions_3": 715, "writing_expressions_w_two_var": 716, "writing_fractions_1": 717, "writing_proportions": 718, "z_scores_1": 719, "z_scores_2": 720, "z_scores_3": 721}